test
ztq_core
