Metadata-Version: 1.1
Name: ztq-core
Version: 1.2.4
Summary: Zopen Task Queue Core
Home-page: http://everydo.com/
Author: edo
Author-email: service@everydo.com
License: MIT
Keywords: Everydo queue ztq_core async
Platform: Any
Classifier: Development Status :: 4 - Beta
Classifier: Environment :: Web Environment
Classifier: Intended Audience :: Developers
Classifier: Programming Language :: Python
Classifier: Operating System :: OS Independent
Classifier: Topic :: Internet :: WWW/HTTP
